amay_key_vault_sdk-1.0.4.dist-info/licenses/LICENSE
key_vault_sdk/__init__.py
key_vault_sdk/client.py
amay_key_vault_sdk-1.0.4.dist-info/METADATA
amay_key_vault_sdk-1.0.4.dist-info/WHEEL
amay_key_vault_sdk-1.0.4.dist-info/top_level.txt
amay_key_vault_sdk-1.0.4.dist-info/RECORD
